css_make/__init__.py
css_make/css.py
css_make/stab.py
css_make/utils.py
css_make-1.3.0.dist-info/LICENSE
css_make-1.3.0.dist-info/METADATA
css_make-1.3.0.dist-info/WHEEL
css_make-1.3.0.dist-info/top_level.txt
css_make-1.3.0.dist-info/RECORD
