Metadata-Version: 2.1
Name: css_make
Version: 1.3.0
Summary: A Python package of the successor to `bp_osd`. Belief propagation with ordered statistics post-processing for decoding quantum LDPC codes.
Author-email: Rambler Stone <keytophy@gmail.com>, Brait <brait.w216@gmail.com>
Maintainer-email: Brait <brait.w216@gmail.com>
License: MIT
Project-URL: Homepage, https://github.com/yysf-brait/css_make
Project-URL: Documentation, https://github.com/yysf-brait/css_make#readme
Classifier: Programming Language :: Python :: 3
Classifier: License :: OSI Approved :: MIT License
Classifier: Operating System :: OS Independent
Requires-Python: >=3.9
License-File: LICENSE
Requires-Dist: numpy>=1.26.0
Requires-Dist: scipy~=1.14.1
Requires-Dist: ldpc~=2.1.2
